.gitignore
MANIFEST.in
README.rst
bootstrap.py
buildout.cfg
setup.py
collective/__init__.py
collective.portlet.oembed.egg-info/PKG-INFO
collective.portlet.oembed.egg-info/SOURCES.txt
collective.portlet.oembed.egg-info/dependency_links.txt
collective.portlet.oembed.egg-info/entry_points.txt
collective.portlet.oembed.egg-info/namespace_packages.txt
collective.portlet.oembed.egg-info/not-zip-safe
collective.portlet.oembed.egg-info/requires.txt
collective.portlet.oembed.egg-info/top_level.txt
collective/portlet/__init__.py
collective/portlet/oembed/__init__.py
collective/portlet/oembed/configure.zcml
collective/portlet/oembed/jsoembed.pt
collective/portlet/oembed/jsoembedall.pt
collective/portlet/oembed/portlet.pt
collective/portlet/oembed/portlet.py
collective/portlet/oembed/upgrades.py
collective/portlet/oembed/upgrades.zcml
collective/portlet/oembed/profiles/default/metadata.xml
collective/portlet/oembed/profiles/default/portlets.xml
collective/portlet/oembed/profiles/default/registry.xml
docs/HISTORY.txt